Workbook

Sheet Assumptions
A1: Pro Forma Assumptions
A3: Operating Assumptions
A4: Tax rate | B4: 0.4
A5: Discount rate (WACC) | B5: 0.08
A6: COGS (% of revenue) | B6: 0.75
A7: Other incremental costs / SG&A (% of revenue) | B7: 0.05
A8: Net working capital (% of revenue) | B8: 0.1
A10: Capital & Depreciation
A11: Depreciable base | B11: =SUM(B25:H25) -> 18000000
A12: Depreciation period (years) | B12: 6
A13: Salvage value (pre-tax) | B13: 1800000
A14: Salvage received in year | B14: 6
A16: Timing
A17: Base year | B17: 2016
A18: Forecast years (n) | B18: 6
A20: Annual Inputs by Year
A21: Year (index) | B21: 0 | C21: =B21+1 -> 1 | D21: =C21+1 -> 2 | E21: =D21+1 -> 3 | F21: =E21+1 -> 4 | G21: =F21+1 -> 5 | H21: =G21+1 -> 6
A22: Calendar year | B22: =B17 -> 2016 | C22: =B22+1 -> 2017 | D22: =C22+1 -> 2018 | E22: =D22+1 -> 2019 | F22: =E22+1 -> 2020 | G22: =F22+1 -> 2021 | H22: =G22+1 -> 2022
A23: Incremental revenues | B23: 0 | C23: 4000000 | D23: 10000000 | E23: 10000000 | F23: 10000000 | G23: 10000000 | H23: 10000000
A24: Cost savings | B24: 0 | C24: 2000000 | D24: 3500000 | E24: 3500000 | F24: 3500000 | G24: 3500000 | H24: 3500000
A25: Capital expenditure (outlay) | B25: 16000000 | C25: 2000000 | D25: 0 | E25: 0 | F25: 0 | G25: 0 | H25: 0

Sheet ProForma
A1: Pro Forma — NPV Calculations
B2: =Assumptions!B22 -> 2016 | C2: =Assumptions!C22 -> 2017 | D2: =Assumptions!D22 -> 2018 | E2: =Assumptions!E22 -> 2019 | F2: =Assumptions!F22 -> 2020 | G2: =Assumptions!G22 -> 2021 | H2: =Assumptions!H22 -> 2022
A3: Year | B3: =Assumptions!B21 -> 0 | C3: =Assumptions!C21 -> 1 | D3: =Assumptions!D21 -> 2 | E3: =Assumptions!E21 -> 3 | F3: =Assumptions!F21 -> 4 | G3: =Assumptions!G21 -> 5 | H3: =Assumptions!H21 -> 6
A5: Calculating unlevered net income
A6: Incremental revenues | B6: =Assumptions!B23 -> 0 | C6: =Assumptions!C23 -> 4000000 | D6: =Assumptions!D23 -> 10000000 | E6: =Assumptions!E23 -> 10000000 | F6: =Assumptions!F23 -> 10000000 | G6: =Assumptions!G23 -> 10000000 | H6: =Assumptions!H23 -> 10000000
A7: - Incremental cost of goods sold | B7: =-Assumptions!$B$6*B6 -> 0 | C7: =-Assumptions!$B$6*C6 -> -3000000 | D7: =-Assumptions!$B$6*D6 -> -7500000 | E7: =-Assumptions!$B$6*E6 -> -7500000 | F7: =-Assumptions!$B$6*F6 -> -7500000 | G7: =-Assumptions!$B$6*G6 -> -7500000 | H7: =-Assumptions!$B$6*H6 -> -7500000
A8: - Other incremental costs | B8: =-Assumptions!$B$7*B6 -> 0 | C8: =-Assumptions!$B$7*C6 -> -200000 | D8: =-Assumptions!$B$7*D6 -> -500000 | E8: =-Assumptions!$B$7*E6 -> -500000 | F8: =-Assumptions!$B$7*F6 -> -500000 | G8: =-Assumptions!$B$7*G6 -> -500000 | H8: =-Assumptions!$B$7*H6 -> -500000
A9: - Depreciation | B9: =IF(AND(B3>=1,B3<=Assumptions!$B$12),-Assumptions!$B$11/Assumptions!$B$12,0) -> 0 | C9: =IF(AND(C3>=1,C3<=Assumptions!$B$12),-Assumptions!$B$11/Assumptions!$B$12,0) -> -3000000 | D9: =IF(AND(D3>=1,D3<=Assumptions!$B$12),-Assumptions!$B$11/Assumptions!$B$12,0) -> -3000000 | E9: =IF(AND(E3>=1,E3<=Assumptions!$B$12),-Assumptions!$B$11/Assumptions!$B$12,0) -> -3000000 | F9: =IF(AND(F3>=1,F3<=Assumptions!$B$12),-Assumptions!$B$11/Assumptions!$B$12,0) -> -3000000 | G9: =IF(AND(G3>=1,G3<=Assumptions!$B$12),-Assumptions!$B$11/Assumptions!$B$12,0) -> -3000000 | H9: =IF(AND(H3>=1,H3<=Assumptions!$B$12),-Assumptions!$B$11/Assumptions!$B$12,0) -> -3000000
A10: - Cost Savings | B10: =Assumptions!B24 -> 0 | C10: =Assumptions!C24 -> 2000000 | D10: =Assumptions!D24 -> 3500000 | E10: =Assumptions!E24 -> 3500000 | F10: =Assumptions!F24 -> 3500000 | G10: =Assumptions!G24 -> 3500000 | H10: =Assumptions!H24 -> 3500000
A11: EBIT | B11: =SUM(B6:B10) -> 0 | C11: =SUM(C6:C10) -> -200000 | D11: =SUM(D6:D10) -> 2500000 | E11: =SUM(E6:E10) -> 2500000 | F11: =SUM(F6:F10) -> 2500000 | G11: =SUM(G6:G10) -> 2500000 | H11: =SUM(H6:H10) -> 2500000
A12: - Taxes | B12: =B11*Assumptions!$B$4 -> 0 | C12: =C11*Assumptions!$B$4 -> -80000 | D12: =D11*Assumptions!$B$4 -> 1000000 | E12: =E11*Assumptions!$B$4 -> 1000000 | F12: =F11*Assumptions!$B$4 -> 1000000 | G12: =G11*Assumptions!$B$4 -> 1000000 | H12: =H11*Assumptions!$B$4 -> 1000000
A13: Unlevered net income | B13: =B11-B12 -> 0 | C13: =C11-C12 -> -120000 | D13: =D11-D12 -> 1500000 | E13: =E11-E12 -> 1500000 | F13: =F11-F12 -> 1500000 | G13: =G11-G12 -> 1500000 | H13: =H11-H12 -> 1500000
A15: Calculating capital expenditures (CapEx)
A16: Initial outlay | B16: =Assumptions!B25 -> 16000000 | C16: =Assumptions!C25 -> 2000000 | D16: =Assumptions!D25 -> 0 | E16: =Assumptions!E25 -> 0 | F16: =Assumptions!F25 -> 0 | G16: =Assumptions!G25 -> 0 | H16: =Assumptions!H25 -> 0
A17: After tax salvage | B17: =IF(B3=Assumptions!$B$14,-Assumptions!$B$13*(1-Assumptions!$B$4),0) -> 0 | C17: =IF(C3=Assumptions!$B$14,-Assumptions!$B$13*(1-Assumptions!$B$4),0) -> 0 | D17: =IF(D3=Assumptions!$B$14,-Assumptions!$B$13*(1-Assumptions!$B$4),0) -> 0 | E17: =IF(E3=Assumptions!$B$14,-Assumptions!$B$13*(1-Assumptions!$B$4),0) -> 0 | F17: =IF(F3=Assumptions!$B$14,-Assumptions!$B$13*(1-Assumptions!$B$4),0) -> 0 | G17: =IF(G3=Assumptions!$B$14,-Assumptions!$B$13*(1-Assumptions!$B$4),0) -> 0 | H17: =IF(H3=Assumptions!$B$14,-Assumptions!$B$13*(1-Assumptions!$B$4),0) -> -1080000
A18: Capital expenditures | B18: =B16+B17 -> 16000000 | C18: =C16+C17 -> 2000000 | D18: =D16+D17 -> 0 | E18: =E16+E17 -> 0 | F18: =F16+F17 -> 0 | G18: =G16+G17 -> 0 | H18: =H16+H17 -> -1080000
A20: Calculating change in net working capital (∆NWC)
A21: Cash requirements
A22: Inventory
A23: Accounts receivable
A24: - Accounts payable
A25: Projected NWC | B25: =IF(B3=Assumptions!$B$18,0,Assumptions!$B$8*B6) -> 0 | C25: =IF(C3=Assumptions!$B$18,0,Assumptions!$B$8*C6) -> 400000 | D25: =IF(D3=Assumptions!$B$18,0,Assumptions!$B$8*D6) -> 1000000 | E25: =IF(E3=Assumptions!$B$18,0,Assumptions!$B$8*E6) -> 1000000 | F25: =IF(F3=Assumptions!$B$18,0,Assumptions!$B$8*F6) -> 1000000 | G25: =IF(G3=Assumptions!$B$18,0,Assumptions!$B$8*G6) -> 1000000 | H25: =IF(H3=Assumptions!$B$18,0,Assumptions!$B$8*H6) -> 0
A26: Change in NWC | B26: =B25 -> 0 | C26: =C25-B25 -> 400000 | D26: =D25-C25 -> 600000 | E26: =E25-D25 -> 0 | F26: =F25-E25 -> 0 | G26: =G25-F25 -> 0 | H26: =H25-G25 -> -1000000
A28: Calculate incremental free cash flows
A29: Unlevered net income + depreciation | B29: =B13-B9 -> 0 | C29: =C13-C9 -> 2880000 | D29: =D13-D9 -> 4500000 | E29: =E13-E9 -> 4500000 | F29: =F13-F9 -> 4500000 | G29: =G13-G9 -> 4500000 | H29: =H13-H9 -> 4500000
A30: - Capital expenditures | B30: =B18 -> 16000000 | C30: =C18 -> 2000000 | D30: =D18 -> 0 | E30: =E18 -> 0 | F30: =F18 -> 0 | G30: =G18 -> 0 | H30: =H18 -> -1080000
A31: - Change in net working capital | B31: =B26 -> 0 | C31: =C26 -> 400000 | D31: =D26 -> 600000 | E31: =E26 -> 0 | F31: =F26 -> 0 | G31: =G26 -> 0 | H31: =H26 -> -1000000
A32: Incremental free cash flow | B32: =B29-B30-B31 -> -16000000 | C32: =C29-C30-C31 -> 480000 | D32: =D29-D30-D31 -> 3900000 | E32: =E29-E30-E31 -> 4500000 | F32: =F29-F30-F31 -> 4500000 | G32: =G29-G30-G31 -> 4500000 | H32: =H29-H30-H31 -> 6580000
A34: Discount rate | B34: =Assumptions!B5 -> 0.08
A35: NPV of investment | B35: =NPV(B34,C32:H32)+B32 -> 1877085.8

Sheet FPV
A1: NPV Calculations
B2: 2016 | C2: 2017 | D2: 2018 | E2: 2019 | F2: 2020 | G2: 2021 | H2: 2022
A3: Year | B3: 0 | C3: 1 | D3: 2 | E3: 3 | F3: 4 | G3: 5 | H3: 6
A5: Calculating unlevered net income
A6: Incremental revenues | C6: 4000000 | D6: 10000000 | E6: 10000000 | F6: 10000000 | G6: 10000000 | H6: 10000000
A7: - Incremental cost of goods sold | C7: =-0.75*C6 -> -3000000 | D7: =-0.75*D6 -> -7500000 | E7: =-0.75*E6 -> -7500000 | F7: =-0.75*F6 -> -7500000 | G7: =-0.75*G6 -> -7500000 | H7: =-0.75*H6 -> -7500000
A8: - Other incremental costs | C8: =-0.05*C6 -> -200000 | D8: =-0.05*D6 -> -500000 | E8: =-0.05*E6 -> -500000 | F8: =-0.05*F6 -> -500000 | G8: =-0.05*G6 -> -500000 | H8: =-0.05*H6 -> -500000
A9: - Depreciation | C9: =-18000000/6 -> -3000000 | D9: =-18000000/6 -> -3000000 | E9: =-18000000/6 -> -3000000 | F9: =-18000000/6 -> -3000000 | G9: =-18000000/6 -> -3000000 | H9: =-18000000/6 -> -3000000
A10: - Cost Savings | C10: 2000000 | D10: 3500000 | E10: 3500000 | F10: 3500000 | G10: 3500000 | H10: 3500000
A11: EBIT | B11: =SUM(B6:B10) -> 0 | C11: =SUM(C6:C10) -> -200000 | D11: =SUM(D6:D10) -> 2500000 | E11: =SUM(E6:E10) -> 2500000 | F11: =SUM(F6:F10) -> 2500000 | G11: =SUM(G6:G10) -> 2500000 | H11: =SUM(H6:H10) -> 2500000
A12: - Taxes (40%) | B12: =B11*0.4 -> 0 | C12: =C11*0.4 -> -80000 | D12: =D11*0.4 -> 1000000 | E12: =E11*0.4 -> 1000000 | F12: =F11*0.4 -> 1000000 | G12: =G11*0.4 -> 1000000 | H12: =H11*0.4 -> 1000000
A13: Unlevered net income | B13: =B11-B12 -> 0 | C13: =C11-C12 -> -120000 | D13: =D11-D12 -> 1500000 | E13: =E11-E12 -> 1500000 | F13: =F11-F12 -> 1500000 | G13: =G11-G12 -> 1500000 | H13: =H11-H12 -> 1500000
A15: Calculating capital expenditures (CapEx)
A16: Initial outlay | B16: 16000000 | C16: 2000000 | D16: 0 | E16: 0 | F16: 0 | G16: 0
A17: After tax salvage | H17: =-1800000*0.6 -> -1080000
A18: Capital expenditures
A20: Calculating change in net working capital (∆NWC)
A21: Cash requirements
A22: Inventory
A23: Accounts receivable
A24: - Accounts payable
A25: Projected NWC | B25: =0.1*B6 -> 0 | C25: =0.1*C6 -> 400000 | D25: =0.1*D6 -> 1000000 | E25: =0.1*E6 -> 1000000 | F25: =0.1*F6 -> 1000000 | G25: =0.1*G6 -> 1000000 | H25: 0
A26: Change in NWC | B26: 0 | C26: =C25 -> 400000 | D26: =D25-C25 -> 600000 | E26: =E25-D25 -> 0 | F26: =F25-E25 -> 0 | G26: =G25-F25 -> 0 | H26: =H25-G25 -> -1000000
A28: Calculate incremental free cash flows
A29: Unlevered net income + depreciation | C29: =C13-C9 -> 2880000 | D29: =D13-D9 -> 4500000 | E29: =E13-E9 -> 4500000 | F29: =F13-F9 -> 4500000 | G29: =G13-G9 -> 4500000 | H29: =H13-H9 -> 4500000
A30: - Capital expenditures | B30: 16000000 | C30: 2000000 | D30: 0 | E30: 0 | F30: 0 | G30: 0 | H30: =H17 -> -1080000
A31: - Change in net working capital | B31: 0 | C31: {=C26:H26} -> 400000 | D31: 600000 | E31: 0 | F31: 0 | G31: 0 | H31: -1000000
A32: Incremental free cash flow | B32: =B29-B30-B31 -> -16000000 | C32: =C29-C30-C31 -> 480000 | D32: =D29-D30-D31 -> 3900000 | E32: =E29-E30-E31 -> 4500000 | F32: =F29-F30-F31 -> 4500000 | G32: =G29-G30-G31 -> 4500000 | H32: =H29-H30-H31 -> 6580000
A34: Discount rate | B34: 0.08
A35: NPV of investment | B35: =NPV(8%,C32:H32)+B32 -> 1877085.8
A37: Discounted Case Flow

Sheet Sensitivity
A1: Sensitivity & Breakeven Analysis
A2: ($ in thousands)
E3: Use solver and set NPV to zero based on value
A4: Assumption | B4: Worst | C4: Base | D4: Best | E4: Breakeven
A6: COGS % | B6: 0.8 | C6: =Assumptions!B6 -> 0.75 | D6: 0.7 | E6: 0.827
A7: NPV | B7: 657 | C7: =ProForma!$B$35/1000 -> 1877.0858 | D7: 3097
A9: SG&A % | B9: 0.075 | C9: =Assumptions!B7 -> 0.05 | D9: 0.025 | E9: 0.127
A10: NPV | B10: 1267 | C10: =ProForma!$B$35/1000 -> 1877.0858 | D10: 2487
A12: Growth rate in savings & revenues | B12: -0.02 | C12: 0 | D12: 0.02 | E12: -0.092
A13: NPV | B13: 1441 | C13: =ProForma!$B$35/1000 -> 1877.0858 | D13: 2330
A15: Net working capital % | B15: 0.15 | C15: =Assumptions!B8 -> 0.1 | D15: 0.05 | E15: 6.94
A16: NPV | B16: 1863 | C16: =ProForma!$B$35/1000 -> 1877.0858 | D16: 1891
A18: Second capital outlay | B18: 4000 | C18: =Assumptions!C25/1000 -> 2000 | D18: 1500 | E18: 5237
A19: NPV | B19: 717 | C19: =ProForma!$B$35/1000 -> 1877.0858 | D19: 2167
A21: Baseline shortwood sales | B21: 8000 | C21: =Assumptions!D23/1000 -> 10000 | D21: 12000 | E21: 5540
A22: NPV | B22: 1035 | C22: =ProForma!$B$35/1000 -> 1877.0858 | D22: 2719
A24: Worst/Best/Breakeven NPVs are scenario outputs. Base column links to the live model (ProForma NPV). To refresh a scenario, enter the assumption value in the Assumptions tab; breakevens are found via Goal Seek.

Sheet Solution
A1: NPV Calculations
A3: Year | B3: 0 | C3: 1 | D3: 2 | E3: 3
A5: Calculating unlevered net income
A6: Incremental revenues | C6: 195000 | D6: 225000 | E6: 250000
A7: - Incremental cost of goods sold | C7: =-0.5*C6 -> -97500 | D7: =-0.5*D6 -> -112500 | E7: =-0.5*E6 -> -125000
A8: - Other incremental costs | C8: -50000 | D8: -50000 | E8: -50000
A9: - Depreciation | C9: =-90000/3 -> -30000 | D9: =-90000/3 -> -30000 | E9: =-90000/3 -> -30000
A10: EBIT | C10: =SUM(C6:C9) -> 17500 | D10: =SUM(D6:D9) -> 32500 | E10: =SUM(E6:E9) -> 45000
A11: - Taxes (25%) | C11: =-C10*0.25 -> -4375 | D11: =-D10*0.25 -> -8125 | E11: =-E10*0.25 -> -11250
A12: Unlevered net income | C12: =SUM(C10:C11) -> 13125 | D12: =SUM(D10:D11) -> 24375 | E12: =SUM(E10:E11) -> 33750
A14: Calculating capital expenditures (CapEx)
A15: Initial outlay | B15: 90000
A16: After tax salvage | E16: =-(10000-0.25*(10000)) -> -7500
A17: Capital expenditures | B17: =B15+B16 -> 90000 | C17: =C15+C16 -> 0 | D17: =D15+D16 -> 0 | E17: =E15+E16 -> -7500
A19: Calculating change in net working capital (∆NWC)
A20: Cash requirements | B20: 0 | C20: 0 | D20: 0 | E20: 0
A21: Inventory | B21: 30000 | C21: =0.2*C6 -> 39000 | D21: =0.2*D6 -> 45000 | E21: 0
A22: Accounts receivable | B22: 0 | C22: 0 | D22: 0 | E22: 0
A23: - Accounts payable | B23: =-15000 -> -15000 | C23: =0.1*C7 -> -9750 | D23: =0.1*D7 -> -11250 | E23: 0
A24: Projected NWC | B24: =SUM(B20:B23) -> 15000 | C24: =SUM(C20:C23) -> 29250 | D24: =SUM(D20:D23) -> 33750 | E24: =SUM(E20:E23) -> 0
A25: Change in NWC | B25: =B24 -> 15000 | C25: =C24-B24 -> 14250 | D25: =D24-C24 -> 4500 | E25: =E24-D24 -> -33750
A27: Calculate incremental free cash flows
A28: Unlevered net income + depreciation | B28: =B12+B9 -> 0 | C28: =C12-C9 -> 43125 | D28: =D12-D9 -> 54375 | E28: =E12-E9 -> 63750
A29: - Capital expenditures | B29: =-B17 -> -90000 | C29: =-C17 -> 0 | D29: =-D17 -> 0 | E29: =-E17 -> 7500
A30: - Change in net working capital | B30: =-B25 -> -15000 | C30: =-C25 -> -14250 | D30: =-D25 -> -4500 | E30: =-E25 -> 33750
A31: Incremental free cash flow | B31: =SUM(B28:B30) -> -105000 | C31: =SUM(C28:C30) -> 28875 | D31: =SUM(D28:D30) -> 49875 | E31: =SUM(E28:E30) -> 105000
A33: Discount rate | B33: 0.08
A34: NPV of investment | B34: =NPV(B33,C31:E31)+B31 -> 47848.27
A37: Two-way Data Tables (for sensitivity analysis)
C38: Incremental revenues in Year 1
B39: =B34 -> 47848.27 | C39: 165000 | D39: 180000 | E39: 195000 | F39: 210000 | G39: 225000
B40: 70000 | C40: 57740.245 | D40: 62794.258 | E40: 67848.27 | F40: 72902.282 | G40: 77956.295
B41: 80000 | C41: 47740.245 | D41: 52794.258 | E41: 57848.27 | F41: 62902.282 | G41: 67956.295
A42: Intitial Outlay | B42: 90000 | C42: 37740.245 | D42: 42794.258 | E42: 47848.27 | F42: 52902.282 | G42: 57956.295
B43: 100000 | C43: 27740.245 | D43: 32794.258 | E43: 37848.27 | F43: 42902.282 | G43: 47956.295
B44: 110000 | C44: 17740.245 | D44: 22794.258 | E44: 27848.27 | F44: 32902.282 | G44: 37956.295

Sheet two Way table
A2: Two-way Data Tables (for sensitivity analysis) | E2: Use What if function under data
B3: Set to NPV formula | C3: Incremental revenues in Year 1
B4: 47848.27 | C4: 165000 | D4: 180000 | E4: 195000 | F4: 210000 | G4: 225000 | H4: Set to row
B5: 70000 | C5: 57740 | D5: 62794 | E5: 67848 | F5: 72902 | G5: 77956
B6: 80000 | C6: 47740 | D6: 52794 | E6: 57848 | F6: 62902 | G6: 67956
A7: Intitial Outlay | B7: 90000 | C7: 37740 | D7: 42794 | E7: 47848 | F7: 52902 | G7: 57956
B8: 100000 | C8: 27740 | D8: 32794 | E8: 37848 | F8: 42902 | G8: 47956
B9: 110000 | C9: 17740 | D9: 22794 | E9: 27848 | F9: 32902 | G9: 37956
A10: Set to column

Sheet Value of a Firm
